magiclan.py
test.py
magiclan2-0.0.2.dist-info/LICENSE
magiclan2-0.0.2.dist-info/METADATA
magiclan2-0.0.2.dist-info/WHEEL
magiclan2-0.0.2.dist-info/top_level.txt
magiclan2-0.0.2.dist-info/RECORD
