Metadata-Version: 2.1
Name: magiclan2
Version: 0.0.2
Summary: MagicLan2 API interface
Home-page: https://github.com/m4rkw/magiclan
Author: Mark Wadham
Author-email: magiclan@rkw.io
License: UNKNOWN
Platform: UNKNOWN
